youtube_mp3-0.1.2.data/scripts/youtube-mp3.py
youtube_mp3-0.1.2.dist-info/DESCRIPTION.rst
youtube_mp3-0.1.2.dist-info/METADATA
youtube_mp3-0.1.2.dist-info/RECORD
youtube_mp3-0.1.2.dist-info/WHEEL
youtube_mp3-0.1.2.dist-info/metadata.json
youtube_mp3-0.1.2.dist-info/top_level.txt
youtubemp3/__init__.py
youtubemp3/youtube-mp3.py
youtubemp3/youtubemp3.py
