Metadata-Version: 2.0
Name: youtube-mp3
Version: 0.1.2
Summary: Python cli and library for youtube-mp3.org.
Home-page: https://github.com/marto1/youtube-mp3
Author: Martin N. Gergov
Author-email: martingergov1@gmail.com
License: MIT/X11
Download-URL: https://github.com/marto1/youtube-mp3
Keywords: youtube-mp3,mp3,youtube,download
Platform: UNKNOWN
Classifier: License :: OSI Approved :: MIT License
Classifier: Topic :: Utilities
Classifier: Topic :: Internet :: WWW/HTTP
Classifier: Topic :: Internet
Classifier: Topic :: Multimedia
Classifier: Programming Language :: Python :: 2.7
Classifier: Programming Language :: Python :: 2
Classifier: Programming Language :: Python :: 3
Classifier: Programming Language :: Python :: 3.4
Classifier: Programming Language :: Python :: 3.5
Requires-Dist: docopt
Requires-Dist: requests
